[
  {
    "id_vehicule": "1202942",
    "num_police": "VO018141",
    "millesime": "2016",
    "date_mec": "2016-07-18",
    "code_genre_vehicule": "VP",
    "nom_marque": "DACIA",
    "nom_carrosserie": "TOUT-TERRAIN",
    "code_energie": "GO",
    "nom_energie": "Diesel",
    "puissance_fiscale": "6",
    "nombre_places": "5",
    "nom_modele": "DUSTER",
    "stock": "177079",
    "kilometrage": "45197",
    "kilometrage_reel": "0",
    "code_couleur": "BLEU COSMOS",
    "prix_vente": "13990",
    "garantie_duree": "6",
    "garantie_nom": "OR 6 MOIS",
    "prix_internet": "0",
    "echange": "",
    "prix_vente_min": "13700",
    "prix_vente_marchand": "0",
    "code_etablissement": "galtC4529",
    "code_groupe": "galt",
    "description_societe": "Grenoble (Renault)",
    "ville": "",
    "nom_version": "dCi 110 4x2 Prestige Edition 2016",
    "nombre_portes": "5",
    "boite_automatique": "0",
    "nombre_rapports": "6",
    "taux_co2": "115",
    "tva_recup": "1",
    "puissance_din": "110",
    "consommation_moyenne": "4",
    "date_disponibilite": "2019-05-06",
    "immatriculation": "ED-899-ZM",
    "description_vendeur": "Auto Dauphine SMH",
    "code_destinataire": "P",
    "code_site": "",
    "prix_devis": "0",
    "tva_devis": "0",
    "numero_chassis": "UU1HSDJ9F55624568",
    "checksum": "4f0e67b18bf4eba6e1e326ab7da585ea96f3cda8",
    "en_avant": "0",
    "en_demo": "0",
    "bonne_affaire": "0",
    "actif": "1",
    "cetelem_mensualite": "327.95",
    "options": [
      "Peinture metallisee",
      "Roue de secours + cric"
    ]
  },
  {
    "id_vehicule": "1202943",
    "num_police": "VO018145",
    "millesime": "2015",
    "date_mec": "2015-08-31",
    "code_genre_vehicule": "VP",
    "nom_marque": "RENAULT",
    "nom_carrosserie": "TOUT-TERRAIN",
    "code_energie": "GO",
    "nom_energie": "Diesel",
    "puissance_fiscale": "5",
    "nombre_places": "5",
    "nom_modele": "CAPTUR",
    "stock": "169480",
    "kilometrage": "44529",
    "kilometrage_reel": "0",
    "code_couleur": "BI-TON GRIS KNG+GNE",
    "prix_vente": "14590",
    "garantie_duree": "6",
    "garantie_nom": "OR 6 MOIS",
    "prix_internet": "0",
    "echange": "",
    "prix_vente_min": "14300",
    "prix_vente_marchand": "0",
    "code_etablissement": "galtC4529",
    "code_groupe": "galt",
    "description_societe": "Grenoble (Renault)",
    "ville": "",
    "nom_version": "dCi 110 Energy Pure",
    "nombre_portes": "5",
    "boite_automatique": "0",
    "nombre_rapports": "6",
    "taux_co2": "98",
    "tva_recup": "1",
    "puissance_din": "110",
    "consommation_moyenne": "3",
    "date_disponibilite": "2019-05-06",
    "immatriculation": "DV-529-JN",
    "description_vendeur": "Auto Dauphine SMH",
    "code_destinataire": "P",
    "code_site": "",
    "prix_devis": "0",
    "tva_devis": "0",
    "numero_chassis": "VF12RAR1C53018986",
    "checksum": "8ee6d36302049f85eb69e4131bb8b95196909915",
    "en_avant": "0",
    "en_demo": "0",
    "bonne_affaire": "0",
    "actif": "1",
    "cetelem_mensualite": "342.02",
    "options": [
      "roue de secours galette"
    ]
  },
  {
    "id_vehicule": "1202533",
    "num_police": "VO082886",
    "millesime": "2017",
    "date_mec": "2017-04-10",
    "code_genre_vehicule": "VP",
    "nom_marque": "RENAULT",
    "nom_carrosserie": "Break",
    "code_energie": "GO",
    "nom_energie": "Diesel",
    "puissance_fiscale": "5",
    "nombre_places": "5",
    "nom_modele": "MEGANE 4 ESTATE",
    "stock": "183478",
    "kilometrage": "13000",
    "kilometrage_reel": "0",
    "code_couleur": "BLEU BERLIN",
    "prix_vente": "20990",
    "garantie_duree": "12",
    "garantie_nom": "OR 12 MOIS",
    "prix_internet": "0",
    "echange": "",
    "prix_vente_min": "20700",
    "prix_vente_marchand": "0",
    "code_etablissement": "galtC112",
    "code_groupe": "galt",
    "description_societe": "Grenoble (Renault)",
    "ville": "",
    "nom_version": "M\u00e9gane IV Estate dCi 110 Energy EDC Intens",
    "nombre_portes": "5",
    "boite_automatique": "1",
    "nombre_rapports": "0",
    "taux_co2": "98",
    "tva_recup": "1",
    "puissance_din": "0",
    "consommation_moyenne": "3",
    "date_disponibilite": "2018-11-13",
    "immatriculation": "EL-978-PA",
    "description_vendeur": "Auto Dauphine Echirolles",
    "code_destinataire": "P",
    "code_site": "SUD",
    "prix_devis": "0",
    "tva_devis": "0",
    "numero_chassis": "VF1RFB00557698197",
    "checksum": "cf78bdeb2d07a940630cc8574a7a043892ed362f",
    "en_avant": "0",
    "en_demo": "0",
    "bonne_affaire": "0",
    "actif": "1",
    "cetelem_mensualite": "490.98",
    "options": [
      "Affichage t\u00eate haute",
      "Pack Easy Parking",
      "Bose Surround System",
      "Jantes alliage 18\" Grand Tour"
    ],
    "photos": [
      "https:\/\/www.autosmanuel.fr\/uploads\/vehicules\/1202533\/VOWPC112_VO082886_149017.jpg",
      "https:\/\/www.autosmanuel.fr\/uploads\/vehicules\/1202533\/VOWPC112_VO082886_149019.jpg",
      "https:\/\/www.autosmanuel.fr\/uploads\/vehicules\/1202533\/VOWPC112_VO082886_149020.jpg",
      "https:\/\/www.autosmanuel.fr\/uploads\/vehicules\/1202533\/VOWPC112_VO082886_149021.jpg",
      "https:\/\/www.autosmanuel.fr\/uploads\/vehicules\/1202533\/VOWPC112_VO082886_149022.jpg",
      "https:\/\/www.autosmanuel.fr\/uploads\/vehicules\/1202533\/VOWPC112_VO082886_149023.jpg",
      "https:\/\/www.autosmanuel.fr\/uploads\/vehicules\/1202533\/VOWPC112_VO082886_149024.jpg",
      "https:\/\/www.autosmanuel.fr\/uploads\/vehicules\/1202533\/VOWPC112_VO082886_149025.jpg",
      "https:\/\/www.autosmanuel.fr\/uploads\/vehicules\/1202533\/VOWPC112_VO082886_149026.jpg",
      "https:\/\/www.autosmanuel.fr\/uploads\/vehicules\/1202533\/VOWPC112_VO082886_149027.jpg",
      "https:\/\/www.autosmanuel.fr\/uploads\/vehicules\/1202533\/VOWPC112_VO082886_149028.jpg",
      "https:\/\/www.autosmanuel.fr\/uploads\/vehicules\/1202533\/VOWPC112_VO082886_149029.jpg",
      "https:\/\/www.autosmanuel.fr\/uploads\/vehicules\/1202533\/VOWPC112_VO082886_149030.jpg",
      "https:\/\/www.autosmanuel.fr\/uploads\/vehicules\/1202533\/VOWPC112_VO082886_149031.jpg"
    ]
  },
  {
    "id_vehicule": "1202534",
    "num_police": "VO082892",
    "millesime": "2016",
    "date_mec": "2016-09-28",
    "code_genre_vehicule": "VP",
    "nom_marque": "RENAULT",
    "nom_carrosserie": "COMBINE",
    "code_energie": "GO",
    "nom_energie": "Diesel",
    "puissance_fiscale": "7",
    "nombre_places": "8",
    "nom_modele": "TRAFIC COMBI",
    "stock": "174979",
    "kilometrage": "41135",
    "kilometrage_reel": "0",
    "code_couleur": "TEINTE CAISSE GRIS PLATINE",
    "prix_vente": "20990",
    "garantie_duree": "6",
    "garantie_nom": "OR 6 MOIS",
    "prix_internet": "0",
    "echange": "",
    "prix_vente_min": "20700",
    "prix_vente_marchand": "0",
    "code_etablissement": "galtC112",
    "code_groupe": "galt",
    "description_societe": "Grenoble (Renault)",
    "ville": "",
    "nom_version": "Trafic Combi L2 dCi 125 Energy Zen",
    "nombre_portes": "4",
    "boite_automatique": "0",
    "nombre_rapports": "6",
    "taux_co2": "0",
    "tva_recup": "1",
    "puissance_din": "0",
    "consommation_moyenne": "5",
    "date_disponibilite": "2018-11-13",
    "immatriculation": "EF-960-PP",
    "description_vendeur": "Auto Dauphine Vizille",
    "code_destinataire": "P",
    "code_site": "VIZILLE",
    "prix_devis": "0",
    "tva_devis": "0",
    "numero_chassis": "VF1JL000X55727991",
    "checksum": "5103c09abd4b38ec902e90e24629bf7fa80466bc",
    "en_avant": "0",
    "en_demo": "0",
    "bonne_affaire": "0",
    "actif": "1",
    "cetelem_mensualite": "490.4",
    "options": [
      "Peinture metallisee",
      "Banquette passager avant 2 places avec rangement sans banquette",
      "Radio CD Connect R&GO\/USB Bluetooth MP3"
    ],
    "photos": [
      "https:\/\/www.autosmanuel.fr\/uploads\/vehicules\/1202534\/VOWPC112_VO082892_149620.jpg",
      "https:\/\/www.autosmanuel.fr\/uploads\/vehicules\/1202534\/VOWPC112_VO082892_142175.jpg",
      "https:\/\/www.autosmanuel.fr\/uploads\/vehicules\/1202534\/VOWPC112_VO082892_142176.jpg",
      "https:\/\/www.autosmanuel.fr\/uploads\/vehicules\/1202534\/VOWPC112_VO082892_142177.jpg",
      "https:\/\/www.autosmanuel.fr\/uploads\/vehicules\/1202534\/VOWPC112_VO082892_142178.jpg",
      "https:\/\/www.autosmanuel.fr\/uploads\/vehicules\/1202534\/VOWPC112_VO082892_142179.jpg",
      "https:\/\/www.autosmanuel.fr\/uploads\/vehicules\/1202534\/VOWPC112_VO082892_142180.jpg",
      "https:\/\/www.autosmanuel.fr\/uploads\/vehicules\/1202534\/VOWPC112_VO082892_142181.jpg",
      "https:\/\/www.autosmanuel.fr\/uploads\/vehicules\/1202534\/VOWPC112_VO082892_142182.jpg",
      "https:\/\/www.autosmanuel.fr\/uploads\/vehicules\/1202534\/VOWPC112_VO082892_142183.jpg",
      "https:\/\/www.autosmanuel.fr\/uploads\/vehicules\/1202534\/VOWPC112_VO082892_142184.jpg",
      "https:\/\/www.autosmanuel.fr\/uploads\/vehicules\/1202534\/VOWPC112_VO082892_142185.jpg",
      "https:\/\/www.autosmanuel.fr\/uploads\/vehicules\/1202534\/VOWPC112_VO082892_142186.jpg",
      "https:\/\/www.autosmanuel.fr\/uploads\/vehicules\/1202534\/VOWPC112_VO082892_142187.jpg"
    ]
  },
  {
    "id_vehicule": "1202531",
    "num_police": "VO082853",
    "millesime": "2016",
    "date_mec": "2016-11-29",
    "code_genre_vehicule": "VP",
    "nom_marque": "RENAULT",
    "nom_carrosserie": "Break",
    "code_energie": "GO",
    "nom_energie": "Diesel",
    "puissance_fiscale": "5",
    "nombre_places": "5",
    "nom_modele": "MEGANE 4 ESTATE",
    "stock": "183478",
    "kilometrage": "41663",
    "kilometrage_reel": "0",
    "code_couleur": "TEINTE CAISSE GRIS PLATINE",
    "prix_vente": "18990",
    "garantie_duree": "6",
    "garantie_nom": "OR 6 MOIS",
    "prix_internet": "0",
    "echange": "",
    "prix_vente_min": "18700",
    "prix_vente_marchand": "0",
    "code_etablissement": "galtC112",
    "code_groupe": "galt",
    "description_societe": "Grenoble (Renault)",
    "ville": "",
    "nom_version": "M\u00e9gane IV Estate dCi 110 Energy EDC Intens",
    "nombre_portes": "5",
    "boite_automatique": "1",
    "nombre_rapports": "0",
    "taux_co2": "95",
    "tva_recup": "1",
    "puissance_din": "0",
    "consommation_moyenne": "3",
    "date_disponibilite": "2018-11-08",
    "immatriculation": "EH-282-CX",
    "description_vendeur": "Auto Dauphine SMH",
    "code_destinataire": "P",
    "code_site": "AUTO DAUPHINE SMH  ",
    "prix_devis": "0",
    "tva_devis": "0",
    "numero_chassis": "VF1RFB00956204297",
    "checksum": "f5cc5a931e24949455b59daa03173f6d59bddfaf",
    "en_avant": "0",
    "en_demo": "0",
    "bonne_affaire": "0",
    "actif": "1",
    "cetelem_mensualite": "443.67",
    "options": [
      "Affichage t\u00eate haute",
      "Regulateur de vitesse adaptatif",
      "Roue de secours",
      "Peinture Gris Platine"
    ],
    "photos": [
      "https:\/\/www.autosmanuel.fr\/uploads\/vehicules\/1202531\/VOWPC112_VO082853_139858.jpg",
      "https:\/\/www.autosmanuel.fr\/uploads\/vehicules\/1202531\/VOWPC112_VO082853_139854.jpg",
      "https:\/\/www.autosmanuel.fr\/uploads\/vehicules\/1202531\/VOWPC112_VO082853_139855.jpg",
      "https:\/\/www.autosmanuel.fr\/uploads\/vehicules\/1202531\/VOWPC112_VO082853_139857.jpg",
      "https:\/\/www.autosmanuel.fr\/uploads\/vehicules\/1202531\/VOWPC112_VO082853_139850.jpg",
      "https:\/\/www.autosmanuel.fr\/uploads\/vehicules\/1202531\/VOWPC112_VO082853_139851.jpg",
      "https:\/\/www.autosmanuel.fr\/uploads\/vehicules\/1202531\/VOWPC112_VO082853_139852.jpg",
      "https:\/\/www.autosmanuel.fr\/uploads\/vehicules\/1202531\/VOWPC112_VO082853_139853.jpg"
    ]
  },
  {
    "id_vehicule": "1202474",
    "num_police": "VO080911",
    "millesime": "2018",
    "date_mec": "2018-03-30",
    "code_genre_vehicule": "VU",
    "nom_marque": "RENAULT",
    "nom_carrosserie": "FOURGONNETTE",
    "code_energie": "GO",
    "nom_energie": "Diesel",
    "puissance_fiscale": "5",
    "nombre_places": "2",
    "nom_modele": "KANGOO Express",
    "stock": "182422",
    "kilometrage": "100",
    "kilometrage_reel": "0",
    "code_couleur": "BLANC MINERAL",
    "prix_vente": "13990",
    "garantie_duree": "24",
    "garantie_nom": "GARANTIE PRO 24",
    "prix_internet": "0",
    "echange": "",
    "prix_vente_min": "13700",
    "prix_vente_marchand": "0",
    "code_etablissement": "galtC112",
    "code_groupe": "galt",
    "description_societe": "Grenoble (Renault)",
    "ville": "",
    "nom_version": "KANGOO EXPRESS 1.5 DCI 75 ENERGY E6 EXTRA R-LINK",
    "nombre_portes": "3",
    "boite_automatique": "0",
    "nombre_rapports": "5",
    "taux_co2": "0",
    "tva_recup": "1",
    "puissance_din": "0",
    "consommation_moyenne": "4",
    "date_disponibilite": "2018-04-09",
    "immatriculation": "EW-177-FV",
    "description_vendeur": "Auto Dauphine SMH",
    "code_destinataire": "P",
    "code_site": "AUTO DAUPHINE SMH  ",
    "prix_devis": "0",
    "tva_devis": "0",
    "numero_chassis": "VF1FW50S159854667",
    "checksum": "4f0d857ef7566f6d430d6ea0ddc3d4c9f7fda6d3",
    "en_avant": "0",
    "en_demo": "0",
    "bonne_affaire": "0",
    "actif": "1",
    "cetelem_mensualite": "326.86",
    "options": [
      "Ordinateur de bord",
      "Volant r\u00e9glable en hauteur",
      "Roue de secours",
      "Climatisation manuelle",
      "Appuis-t\u00eate AV r\u00e9glables en hauteur",
      "Ceintures de s\u00e9curit\u00e9 AV r\u00e9glables en hauteur",
      "Cloison compl\u00e8te t\u00f4l\u00e9e",
      "Compte-tours",
      "Ceintures de s\u00e9curit\u00e9 AV avec pr\u00e9tensionneurs et limiteurs d'effort",
      "Direction assist\u00e9e \u00e9lectrique \u00e0 assistance variable",
      "Condamnation automatique des ouvrants en roulant (CAR)",
      "Cl\u00e9 2 boutons",
      "Bacs de rangement dans les panneaux de portes AV",
      "Barres de protection derri\u00e8re le conducteur",
      "Condamnation centralis\u00e9e des portes par t\u00e9l\u00e9commande \u00e0 radiofr\u00e9quence",
      "Connectique dans zone de chargement",
      "Console centrale de rangement entre les si\u00e8ges AV",
      "Eclaireur central AV 3 positions",
      "Eclairage de la zone de chargement",
      "Fonction \u00e9clairage d'accompagnement ext\u00e9rieur (Follow me home)",
      "Pr\u00e9disposition barres de toit et galerie",
      "Rangement format A4 en planche de bord",
      "Syst\u00e8me antid\u00e9marrage command\u00e9 par cl\u00e9 \u00e0 transpondeur",
      "Tapis habitacle plastique Noir",
      "Vitres teint\u00e9es \u00e0 pouvoir filtrant",
      "Rack de rangement sup\u00e9rieur (capucine)",
      "Alarme sonore de non extinction des feux et voyant de fermeture des portes",
      "Bo\u00eete \u00e0 grande capacit\u00e9",
      "Anneaux d'arrimage au sol dans la zone de chargement",
      "R\u00e9gulateur limiteur de vitesse"
    ]
  },
  {
    "id_vehicule": "1202475",
    "num_police": "VO080912",
    "millesime": "2018",
    "date_mec": "2018-03-30",
    "code_genre_vehicule": "VU",
    "nom_marque": "RENAULT",
    "nom_carrosserie": "FOURGONNETTE",
    "code_energie": "GO",
    "nom_energie": "Diesel",
    "puissance_fiscale": "5",
    "nombre_places": "2",
    "nom_modele": "KANGOO Express",
    "stock": "182422",
    "kilometrage": "10",
    "kilometrage_reel": "1",
    "code_couleur": "BLANC MINERAL",
    "prix_vente": "13990",
    "garantie_duree": "24",
    "garantie_nom": "GARANTIE PRO 24",
    "prix_internet": "0",
    "echange": "",
    "prix_vente_min": "13700",
    "prix_vente_marchand": "12500",
    "code_etablissement": "galtC112",
    "code_groupe": "galt",
    "description_societe": "Grenoble (Renault)",
    "ville": "",
    "nom_version": "KANGOO EXPRESS 1.5 DCI 75 ENERGY E6 EXTRA R-LINK",
    "nombre_portes": "3",
    "boite_automatique": "0",
    "nombre_rapports": "5",
    "taux_co2": "0",
    "tva_recup": "1",
    "puissance_din": "0",
    "consommation_moyenne": "4",
    "date_disponibilite": "2018-04-09",
    "immatriculation": "EW-322-FV",
    "description_vendeur": "Auto Dauphine Echirolles",
    "code_destinataire": "P",
    "code_site": "SUD",
    "prix_devis": "0",
    "tva_devis": "0",
    "numero_chassis": "VF1FW50S159939034",
    "checksum": "07c616c9f3e3bfb010d6b002b7f333d8de8be19b",
    "en_avant": "0",
    "en_demo": "0",
    "bonne_affaire": "0",
    "actif": "1",
    "cetelem_mensualite": "327.24",
    "options": [
      "Pack Cloison Pivotante"
    ],
    "photos": [
      "https:\/\/www.autosmanuel.fr\/uploads\/vehicules\/1202475\/VOWPC112_VO080912_127002.jpg",
      "https:\/\/www.autosmanuel.fr\/uploads\/vehicules\/1202475\/VOWPC112_VO080912_127003.jpg",
      "https:\/\/www.autosmanuel.fr\/uploads\/vehicules\/1202475\/VOWPC112_VO080912_127004.jpg",
      "https:\/\/www.autosmanuel.fr\/uploads\/vehicules\/1202475\/VOWPC112_VO080912_127005.jpg",
      "https:\/\/www.autosmanuel.fr\/uploads\/vehicules\/1202475\/VOWPC112_VO080912_127006.jpg",
      "https:\/\/www.autosmanuel.fr\/uploads\/vehicules\/1202475\/VOWPC112_VO080912_127007.jpg",
      "https:\/\/www.autosmanuel.fr\/uploads\/vehicules\/1202475\/VOWPC112_VO080912_127008.jpg",
      "https:\/\/www.autosmanuel.fr\/uploads\/vehicules\/1202475\/VOWPC112_VO080912_127009.jpg",
      "https:\/\/www.autosmanuel.fr\/uploads\/vehicules\/1202475\/VOWPC112_VO080912_127010.jpg",
      "https:\/\/www.autosmanuel.fr\/uploads\/vehicules\/1202475\/VOWPC112_VO080912_127011.jpg",
      "https:\/\/www.autosmanuel.fr\/uploads\/vehicules\/1202475\/VOWPC112_VO080912_127012.jpg",
      "https:\/\/www.autosmanuel.fr\/uploads\/vehicules\/1202475\/VOWPC112_VO080912_127013.jpg",
      "https:\/\/www.autosmanuel.fr\/uploads\/vehicules\/1202475\/VOWPC112_VO080912_127014.jpg",
      "https:\/\/www.autosmanuel.fr\/uploads\/vehicules\/1202475\/VOWPC112_VO080912_127015.jpg",
      "https:\/\/www.autosmanuel.fr\/uploads\/vehicules\/1202475\/VOWPC112_VO080912_127016.jpg"
    ]
  },
  {
    "id_vehicule": "1202476",
    "num_police": "VO080927",
    "millesime": "2016",
    "date_mec": "2016-09-15",
    "code_genre_vehicule": "VP",
    "nom_marque": "RENAULT",
    "nom_carrosserie": "Berline",
    "code_energie": "GO",
    "nom_energie": "Diesel",
    "puissance_fiscale": "7",
    "nombre_places": "5",
    "nom_modele": "KADJAR",
    "stock": "173001",
    "kilometrage": "42898",
    "kilometrage_reel": "0",
    "code_couleur": "BEIGE DUNE",
    "prix_vente": "19290",
    "garantie_duree": "6",
    "garantie_nom": "OR 6 MOIS",
    "prix_internet": "0",
    "echange": "",
    "prix_vente_min": "19000",
    "prix_vente_marchand": "0",
    "code_etablissement": "galtC112",
    "code_groupe": "galt",
    "description_societe": "Grenoble (Renault)",
    "ville": "",
    "nom_version": "dCi 130 Energy Edition One",
    "nombre_portes": "5",
    "boite_automatique": "0",
    "nombre_rapports": "6",
    "taux_co2": "117",
    "tva_recup": "1",
    "puissance_din": "0",
    "consommation_moyenne": "4",
    "date_disponibilite": "2018-04-10",
    "immatriculation": "EF-902-FN",
    "description_vendeur": "Auto Dauphine SMH",
    "code_destinataire": "P",
    "code_site": "AUTO DAUPHINE SMH  ",
    "prix_devis": "0",
    "tva_devis": "0",
    "numero_chassis": "VF1RFE00354474347",
    "checksum": "bd9e24fa97673904e6144a58606bf88b786e80f0",
    "en_avant": "0",
    "en_demo": "0",
    "bonne_affaire": "0",
    "actif": "1",
    "cetelem_mensualite": "451.21",
    "options": [
      "roue de secours galette",
      "Peinture Beige Dune",
      "Extended Grip jantes alliage 17\" Aquila et pneus tout temps"
    ],
    "photos": [
      "https:\/\/www.autosmanuel.fr\/uploads\/vehicules\/1202476\/VOWPC112_VO080927_138282.jpg",
      "https:\/\/www.autosmanuel.fr\/uploads\/vehicules\/1202476\/VOWPC112_VO080927_129767.jpg",
      "https:\/\/www.autosmanuel.fr\/uploads\/vehicules\/1202476\/VOWPC112_VO080927_129768.jpg",
      "https:\/\/www.autosmanuel.fr\/uploads\/vehicules\/1202476\/VOWPC112_VO080927_129769.jpg",
      "https:\/\/www.autosmanuel.fr\/uploads\/vehicules\/1202476\/VOWPC112_VO080927_129770.jpg",
      "https:\/\/www.autosmanuel.fr\/uploads\/vehicules\/1202476\/VOWPC112_VO080927_129771.jpg",
      "https:\/\/www.autosmanuel.fr\/uploads\/vehicules\/1202476\/VOWPC112_VO080927_129772.jpg",
      "https:\/\/www.autosmanuel.fr\/uploads\/vehicules\/1202476\/VOWPC112_VO080927_129773.jpg",
      "https:\/\/www.autosmanuel.fr\/uploads\/vehicules\/1202476\/VOWPC112_VO080927_129774.jpg",
      "https:\/\/www.autosmanuel.fr\/uploads\/vehicules\/1202476\/VOWPC112_VO080927_129775.jpg",
      "https:\/\/www.autosmanuel.fr\/uploads\/vehicules\/1202476\/VOWPC112_VO080927_129776.jpg",
      "https:\/\/www.autosmanuel.fr\/uploads\/vehicules\/1202476\/VOWPC112_VO080927_129777.jpg",
      "https:\/\/www.autosmanuel.fr\/uploads\/vehicules\/1202476\/VOWPC112_VO080927_129778.jpg",
      "https:\/\/www.autosmanuel.fr\/uploads\/vehicules\/1202476\/VOWPC112_VO080927_129779.jpg",
      "https:\/\/www.autosmanuel.fr\/uploads\/vehicules\/1202476\/VOWPC112_VO080927_129780.jpg"
    ]
  },
  {
    "id_vehicule": "1202471",
    "num_police": "VO079040",
    "millesime": "2017",
    "date_mec": "2017-01-30",
    "code_genre_vehicule": "VP",
    "nom_marque": "RENAULT",
    "nom_carrosserie": "MONOSPACE",
    "code_energie": "GO",
    "nom_energie": "Diesel",
    "puissance_fiscale": "5",
    "nombre_places": "5",
    "nom_modele": "SCENIC 4",
    "stock": "187101",
    "kilometrage": "34300",
    "kilometrage_reel": "0",
    "code_couleur": "BEIGE",
    "prix_vente": "17990",
    "garantie_duree": "12",
    "garantie_nom": "OR 12 MOIS",
    "prix_internet": "0",
    "echange": "",
    "prix_vente_min": "17800",
    "prix_vente_marchand": "0",
    "code_etablissement": "galtC112",
    "code_groupe": "galt",
    "description_societe": "Grenoble (Renault)",
    "ville": "",
    "nom_version": "Scenic dCi 110 Energy Business",
    "nombre_portes": "5",
    "boite_automatique": "0",
    "nombre_rapports": "6",
    "taux_co2": "100",
    "tva_recup": "1",
    "puissance_din": "0",
    "consommation_moyenne": "3",
    "date_disponibilite": "2017-08-31",
    "immatriculation": "EJ-033-RH",
    "description_vendeur": "Auto Dauphine Vizille",
    "code_destinataire": "P",
    "code_site": "VIZILLE",
    "prix_devis": "0",
    "tva_devis": "0",
    "numero_chassis": "VF1RFA00657110785",
    "checksum": "1e34c90327fa0ae444e4e4b4539f9fd9a28631cb",
    "en_avant": "0",
    "en_demo": "0",
    "bonne_affaire": "0",
    "actif": "1",
    "cetelem_mensualite": "420.31",
    "options": [
      "roue de secours galette",
      "Peinture Beige Dune"
    ],
    "photos": [
      "https:\/\/www.autosmanuel.fr\/uploads\/vehicules\/1202471\/VOWPC112_VO079040_122321.jpg",
      "https:\/\/www.autosmanuel.fr\/uploads\/vehicules\/1202471\/VOWPC112_VO079040_118739.jpg",
      "https:\/\/www.autosmanuel.fr\/uploads\/vehicules\/1202471\/VOWPC112_VO079040_118740.jpg",
      "https:\/\/www.autosmanuel.fr\/uploads\/vehicules\/1202471\/VOWPC112_VO079040_118741.jpg",
      "https:\/\/www.autosmanuel.fr\/uploads\/vehicules\/1202471\/VOWPC112_VO079040_118742.jpg",
      "https:\/\/www.autosmanuel.fr\/uploads\/vehicules\/1202471\/VOWPC112_VO079040_118743.jpg",
      "https:\/\/www.autosmanuel.fr\/uploads\/vehicules\/1202471\/VOWPC112_VO079040_118744.jpg",
      "https:\/\/www.autosmanuel.fr\/uploads\/vehicules\/1202471\/VOWPC112_VO079040_118745.jpg",
      "https:\/\/www.autosmanuel.fr\/uploads\/vehicules\/1202471\/VOWPC112_VO079040_118746.jpg",
      "https:\/\/www.autosmanuel.fr\/uploads\/vehicules\/1202471\/VOWPC112_VO079040_118747.jpg",
      "https:\/\/www.autosmanuel.fr\/uploads\/vehicules\/1202471\/VOWPC112_VO079040_118748.jpg",
      "https:\/\/www.autosmanuel.fr\/uploads\/vehicules\/1202471\/VOWPC112_VO079040_118749.jpg",
      "https:\/\/www.autosmanuel.fr\/uploads\/vehicules\/1202471\/VOWPC112_VO079040_118750.jpg",
      "https:\/\/www.autosmanuel.fr\/uploads\/vehicules\/1202471\/VOWPC112_VO079040_118751.jpg",
      "https:\/\/www.autosmanuel.fr\/uploads\/vehicules\/1202471\/VOWPC112_VO079040_118752.jpg"
    ]
  },
  {
    "id_vehicule": "1202763",
    "num_police": "VO017355",
    "millesime": "2018",
    "date_mec": "2018-03-16",
    "code_genre_vehicule": "VP",
    "nom_marque": "RENAULT",
    "nom_carrosserie": "Berline",
    "code_energie": "GO",
    "nom_energie": "Diesel",
    "puissance_fiscale": "6",
    "nombre_places": "5",
    "nom_modele": "TALISMAN",
    "stock": "196136",
    "kilometrage": "10",
    "kilometrage_reel": "1",
    "code_couleur": "GRIS",
    "prix_vente": "21990",
    "garantie_duree": "24",
    "garantie_nom": "GTIE OR 24 MOIS",
    "prix_internet": "0",
    "echange": "",
    "prix_vente_min": "21790",
    "prix_vente_marchand": "0",
    "code_etablissement": "galtC4366",
    "code_groupe": "galt",
    "description_societe": "rives sur fures",
    "ville": "",
    "nom_version": "dCi 130 Energy Limited",
    "nombre_portes": "4",
    "boite_automatique": "0",
    "nombre_rapports": "6",
    "taux_co2": "102",
    "tva_recup": "1",
    "puissance_din": "0",
    "consommation_moyenne": "3",
    "date_disponibilite": "2018-04-04",
    "immatriculation": "EV-259-VA",
    "description_vendeur": "Auto Dauphine Rives",
    "code_destinataire": "P",
    "code_site": "RIVES",
    "prix_devis": "0",
    "tva_devis": "0",
    "numero_chassis": "VF1RFD00258975880",
    "checksum": "36aabd2351ee4014f524b6601a9df9637cce1f31",
    "en_avant": "0",
    "en_demo": "0",
    "bonne_affaire": "0",
    "actif": "1",
    "cetelem_mensualite": "515.49",
    "options": [
      "roue de secours galette"
    ],
    "photos": [
      "https:\/\/www.autosmanuel.fr\/uploads\/vehicules\/1202763\/VOWPC4366_VO017355_126798.jpg",
      "https:\/\/www.autosmanuel.fr\/uploads\/vehicules\/1202763\/VOWPC4366_VO017355_126800.jpg",
      "https:\/\/www.autosmanuel.fr\/uploads\/vehicules\/1202763\/VOWPC4366_VO017355_126801.jpg",
      "https:\/\/www.autosmanuel.fr\/uploads\/vehicules\/1202763\/VOWPC4366_VO017355_126802.jpg",
      "https:\/\/www.autosmanuel.fr\/uploads\/vehicules\/1202763\/VOWPC4366_VO017355_126803.jpg",
      "https:\/\/www.autosmanuel.fr\/uploads\/vehicules\/1202763\/VOWPC4366_VO017355_126804.jpg",
      "https:\/\/www.autosmanuel.fr\/uploads\/vehicules\/1202763\/VOWPC4366_VO017355_126805.jpg",
      "https:\/\/www.autosmanuel.fr\/uploads\/vehicules\/1202763\/VOWPC4366_VO017355_126806.jpg",
      "https:\/\/www.autosmanuel.fr\/uploads\/vehicules\/1202763\/VOWPC4366_VO017355_126807.jpg"
    ]
  }
]